[
  {
    "id": "1",
    "title": "Data Science Basics",
    "description": "Fundamental concepts of data science",
    "cards": [
      {
        "id": "1",
        "front": "What is data science?",
        "back": "Extracting insights from data using scientific methods, statistics, and programming."
      },
      {
        "id": "2",
        "front": "What is the most important language for data science?",
        "back": "Python - due to its simplicity and extensive libraries."
      },
      {
        "id": "3",
        "front": "What is machine learning?",
        "back": "A subset of AI that automates analytical model building from data."
      },
      {
        "id": "4",
        "front": "Difference between AI and ML?",
        "back": "AI is broader (encompassing ML and other approaches), ML is a subset focused on learning from data."
      },
      {
        "id": "5",
        "front": "What is big data?",
        "back": "Datasets too large or complex for traditional data processing tools."
      }
    ]
  },
  {
    "id": "2",
    "title": "Python Libraries",
    "description": "Essential Python libraries for data science",
    "cards": [
      {
        "id": "1",
        "front": "What is NumPy used for?",
        "back": "Numerical computing, multi-dimensional arrays, and mathematical functions."
      },
      {
        "id": "2",
        "front": "What is pandas used for?",
        "back": "Data manipulation and analysis with DataFrame and Series structures."
      },
      {
        "id": "3",
        "front": "What is matplotlib used for?",
        "back": "Creating static, animated, and interactive visualizations."
      },
      {
        "id": "4",
        "front": "What is scikit-learn?",
        "back": "A machine learning library providing tools for predictive data analysis."
      },
      {
        "id": "5",
        "front": "What is Jupyter Notebook?",
        "back": "An interactive computing environment for creating documents with live code."
      }
    ]
  },
  {
    "id": "3",
    "title": "Data Preparation",
    "description": "Cleaning and preparing data for analysis",
    "cards": [
      {
        "id": "1",
        "front": "What is data cleaning?",
        "back": "Removing errors, inconsistencies, and irrelevant data from datasets."
      },
      {
        "id": "2",
        "front": "What is ETL?",
        "back": "Extract, Transform, Load - the process of preparing data for analysis."
      },
      {
        "id": "3",
        "front": "What are missing values?",
        "back": "Data points that are not available or recorded for a variable."
      },
      {
        "id": "4",
        "front": "What is data normalization?",
        "back": "Scaling numeric variables to a standard range, usually 0 to 1."
      },
      {
        "id": "5",
        "front": "What is feature engineering?",
        "back": "Creating new input features from existing data to improve model performance."
      }
    ]
  },
  {
    "id": "4",
    "title": "EDA - Exploratory Data Analysis",
    "description": "Understanding and exploring datasets",
    "cards": [
      {
        "id": "1",
        "front": "What is EDA?",
        "back": "Exploratory Data Analysis - analyzing datasets to summarize main characteristics."
      },
      {
        "id": "2",
        "front": "What is a histogram used for?",
        "back": "Showing the frequency distribution of a single continuous variable."
      },
      {
        "id": "3",
        "front": "What is a scatter plot used for?",
        "back": "Displaying the relationship between two continuous variables."
      },
      {
        "id": "4",
        "front": "What is correlation?",
        "back": "A statistical measure of the relationship between two variables."
      },
      {
        "id": "5",
        "front": "What is a box plot used for?",
        "back": "Showing data distribution, median, quartiles, and potential outliers."
      }
    ]
  },
  {
    "id": "5",
    "title": "Statistics Fundamentals",
    "description": "Essential statistical concepts",
    "cards": [
      {
        "id": "1",
        "front": "What is the mean?",
        "back": "The average of a set of numbers, calculated by summing and dividing by count."
      },
      {
        "id": "2",
        "front": "What is standard deviation?",
        "back": "A measure of data spread around the mean; square root of variance."
      },
      {
        "id": "3",
        "front": "What is a normal distribution?",
        "back": "A bell-shaped probability distribution symmetric around the mean."
      },
      {
        "id": "4",
        "front": "What is hypothesis testing?",
        "back": "Testing claims about populations using sample data and statistical methods."
      },
      {
        "id": "5",
        "front": "What is a p-value?",
        "back": "The probability of observing data if the null hypothesis is true."
      }
    ]
  },
  {
    "id": "6",
    "title": "Supervised Learning",
    "description": "Machine learning with labeled data",
    "cards": [
      {
        "id": "1",
        "front": "What is supervised learning?",
        "back": "Learning from labeled training data to predict outputs for new inputs."
      },
      {
        "id": "2",
        "front": "What is regression?",
        "back": "Predicting continuous numerical values based on input features."
      },
      {
        "id": "3",
        "front": "What is classification?",
        "back": "Predicting discrete categories or classes for input data."
      },
      {
        "id": "4",
        "front": "What is overfitting?",
        "back": "When a model performs well on training data but poorly on new data."
      },
      {
        "id": "5",
        "front": "What is cross-validation?",
        "back": "A technique to assess model performance by splitting data multiple ways."
      }
    ]
  },
  {
    "id": "7",
    "title": "Unsupervised Learning",
    "description": "Machine learning with unlabeled data",
    "cards": [
      {
        "id": "1",
        "front": "What is unsupervised learning?",
        "back": "Finding patterns in data without labeled examples or supervision."
      },
      {
        "id": "2",
        "front": "What is clustering?",
        "back": "Grouping similar data points together based on characteristics."
      },
      {
        "id": "3",
        "front": "What is K-means?",
        "back": "A centroid-based clustering algorithm that partitions data into k clusters."
      },
      {
        "id": "4",
        "front": "What is PCA?",
        "back": "Principal Component Analysis - reduces dimensionality while preserving variance."
      },
      {
        "id": "5",
        "front": "What is anomaly detection?",
        "back": "Finding data points that deviate significantly from normal behavior."
      }
    ]
  },
  {
    "id": "8",
    "title": "Deep Learning",
    "description": "Neural networks and deep learning",
    "cards": [
      {
        "id": "1",
        "front": "What is deep learning?",
        "back": "A subset of ML using neural networks with multiple hidden layers."
      },
      {
        "id": "2",
        "front": "What is a neural network?",
        "back": "A computing system inspired by biological neural networks."
      },
      {
        "id": "3",
        "front": "What is backpropagation?",
        "back": "An algorithm for training neural networks by calculating gradients."
      },
      {
        "id": "4",
        "front": "What is TensorFlow?",
        "back": "An open-source framework for building and training ML models."
      },
      {
        "id": "5",
        "front": "What is PyTorch?",
        "back": "A Python-based scientific computing package for deep learning."
      }
    ]
  },
  {
    "id": "9",
    "title": "Ethics & Best Practices",
    "description": "Ethical considerations in data science",
    "cards": [
      {
        "id": "1",
        "front": "What is data privacy?",
        "back": "Protecting personal information from unauthorized access and misuse."
      },
      {
        "id": "2",
        "front": "What is bias in ML?",
        "back": "Systematic errors that can disadvantage certain groups or produce unfair results."
      },
      {
        "id": "3",
        "front": "What is GDPR?",
        "back": "General Data Protection Regulation - EU regulation for data protection."
      },
      {
        "id": "4",
        "front": "What is reproducible research?",
        "back": "Research that can be replicated and verified by others."
      },
      {
        "id": "5",
        "front": "What is data governance?",
        "back": "Managing data availability, usability, integrity, and security."
      }
    ]
  },
  {
    "id": "10",
    "title": "Production Data Science",
    "description": "Deploying and maintaining models",
    "cards": [
      {
        "id": "1",
        "front": "What is model deployment?",
        "back": "Making a trained model available for use in production applications."
      },
      {
        "id": "2",
        "front": "What is MLOps?",
        "back": "Machine Learning Operations - applying DevOps to ML development."
      },
      {
        "id": "3",
        "front": "What is model monitoring?",
        "back": "Tracking model performance and behavior in production environments."
      },
      {
        "id": "4",
        "front": "What is A/B testing?",
        "back": "Comparing two versions of a model or feature to determine which performs better."
      },
      {
        "id": "5",
        "front": "What is model retraining?",
        "back": "Updating a model with new data to maintain performance over time."
      }
    ]
  }
]